elementflow.py
elementflow-0.5.dist-info/top_level.txt
elementflow-0.5.dist-info/WHEEL
elementflow-0.5.dist-info/DESCRIPTION.rst
elementflow-0.5.dist-info/RECORD
elementflow-0.5.dist-info/METADATA
elementflow-0.5.dist-info/metadata.json
