Metadata-Version: 2.0
Name: elementflow
Version: 0.5
Summary: Python library for generating XML as a stream without building a tree in memory.
Home-page: https://github.com/isagalaev/elementflow
Author: Ivan Sagalaev
Author-email: maniac@softwaremaniacs.org
License: BSD
Platform: UNKNOWN
Classifier: Development Status :: 5 - Production/Stable
Classifier: License :: OSI Approved :: BSD License
Classifier: Programming Language :: Python :: 2
Classifier: Programming Language :: Python :: 3
Classifier: Topic :: Software Development :: Libraries :: Python Modules
Requires-Dist: six
